kognic/studioloader/__init__.py
kognic/studioloader/_version.py
kognic/studioloader/app.py
kognic/studioloader/client.py
kognic/studioloader/connection_handler.py
kognic/studioloader/logging_utils.py
kognic/studioloader/protobuf.py
kognic/studioloader/resource_parser.py
kognic/studioloader/server.py
kognic/studioloader/server_handler.py
kognic/studioloader/interfaces/loader.py
kognic/studioloader/interfaces/warehouse.py
kognic/studioloader/loader/kognic_io_loader.py
kognic/studioloader/loader/poc_data_loader.py
kognic/studioloader/loader/zod_loader.py
kognic/studioloader/warehouse/everything_warehouse.py
kognic/studioloader/warehouse/kognic_io_warehouse.py
kognic/studioloader/warehouse/poc_data_warehouse.py
kognic/studioloader/warehouse/zod_warehouse.py
kognic_studioloader-0.1.8.data/scripts/zod-server
kognic_studioloader-0.1.8.dist-info/METADATA
kognic_studioloader-0.1.8.dist-info/WHEEL
kognic_studioloader-0.1.8.dist-info/entry_points.txt
kognic_studioloader-0.1.8.dist-info/top_level.txt
kognic_studioloader-0.1.8.dist-info/RECORD
